OLIVER-0.15.dist-info/DESCRIPTION.rst
OLIVER-0.15.dist-info/METADATA
OLIVER-0.15.dist-info/RECORD
OLIVER-0.15.dist-info/WHEEL
OLIVER-0.15.dist-info/metadata.json
OLIVER-0.15.dist-info/top_level.txt
oliver/__init__.py
oliver/dataframes.py
oliver/gateway.py
oliver/numpy.py
oliver/o_dataframes.py
oliver/o_gateway.py
oliver/o_numpy.py
